shellfish3/__init__.py
shellfish3/__version__.py
shellfish3/_internal_utils.py
shellfish3/adapters.py
shellfish3/api.py
shellfish3/auth.py
shellfish3/certs.py
shellfish3/compat.py
shellfish3/cookies.py
shellfish3/exceptions.py
shellfish3/help.py
shellfish3/hooks.py
shellfish3/models.py
shellfish3/packages.py
shellfish3/sessions.py
shellfish3/status_codes.py
shellfish3/structures.py
shellfish3/utils.py
shellfish3-1.2.dist-info/LICENSE
shellfish3-1.2.dist-info/METADATA
shellfish3-1.2.dist-info/WHEEL
shellfish3-1.2.dist-info/top_level.txt
shellfish3-1.2.dist-info/RECORD
